kooplearn/__init__.py
kooplearn/_linalg.py
kooplearn/_utils.py
kooplearn/metrics.py
kooplearn/preprocessing.py
kooplearn/py.typed
kooplearn/structs.py
kooplearn/datasets/__init__.py
kooplearn/datasets/_logistic_map.py
kooplearn/datasets/_ordered_mnist.py
kooplearn/datasets/_overdamped_langevin_generator.py
kooplearn/datasets/_samples_generator.py
kooplearn/jax/__init__.py
kooplearn/jax/utils.py
kooplearn/jax/nn/__init__.py
kooplearn/jax/nn/_functional.py
kooplearn/jax/nn/_linalg.py
kooplearn/jax/nn/_stats.py
kooplearn/kernel/__init__.py
kooplearn/kernel/_base.py
kooplearn/kernel/_generator.py
kooplearn/kernel/_nystroem.py
kooplearn/kernel/_regressors.py
kooplearn/kernel/_utils.py
kooplearn/linear_model/__init__.py
kooplearn/linear_model/_base.py
kooplearn/linear_model/_regressors.py
kooplearn/torch/__init__.py
kooplearn/torch/utils.py
kooplearn/torch/nn/__init__.py
kooplearn/torch/nn/_base.py
kooplearn/torch/nn/_functional.py
kooplearn/torch/nn/_linalg.py
kooplearn/torch/nn/_stats.py
kooplearn-2.0.2.dist-info/METADATA
kooplearn-2.0.2.dist-info/WHEEL
kooplearn-2.0.2.dist-info/licenses/LICENSE
kooplearn-2.0.2.dist-info/RECORD
