Metadata-Version: 2.4
Name: kooplearn
Version: 2.0.2
Summary: A python package for evolution operator learning
Author: the kooplearn authors
License-File: LICENSE
Requires-Python: >=3.10
Requires-Dist: pandas>=2.3.3
Requires-Dist: scikit-learn>=1.6.1
Provides-Extra: jax
Requires-Dist: flax>=0.8.5; extra == 'jax'
Requires-Dist: jax>=0.4.30; extra == 'jax'
Provides-Extra: torch
Requires-Dist: torch>=2.6; extra == 'torch'
